ColorSky/ColorSky.py
ColorSky/__init__.py
ColorSky-1.2.1.data/data/LICENSE
ColorSky-1.2.1.dist-info/LICENSE
ColorSky-1.2.1.dist-info/METADATA
ColorSky-1.2.1.dist-info/WHEEL
ColorSky-1.2.1.dist-info/top_level.txt
ColorSky-1.2.1.dist-info/RECORD
